django_metachoices-0.1.6.dist-info/licenses/LICENSE
metachoices/__init__.py
metachoices/admin.py
metachoices/apps.py
metachoices/fields.py
metachoices/mixins.py
metachoices/models.py
metachoices/py.typed
metachoices/views.py
metachoices/migrations/0001_initial.py
metachoices/migrations/0002_storage_count.py
metachoices/migrations/0003_alter_storage_count.py
metachoices/migrations/__init__.py
django_metachoices-0.1.6.dist-info/METADATA
django_metachoices-0.1.6.dist-info/WHEEL
django_metachoices-0.1.6.dist-info/top_level.txt
django_metachoices-0.1.6.dist-info/RECORD
