Metadata-Version: 2.4
Name: django-metachoices
Version: 0.1.6
Summary: A Django field extension that allows choices to have rich metadata beyond the standard (value, display) tuple
Author-email: Luqmaan <luqmaansu@gmail.com>
Maintainer-email: Luqmaan <luqmaansu@gmail.com>
License-Expression: MIT
Project-URL: Homepage, https://github.com/luqmaansu/django-metachoices
Project-URL: Documentation, https://github.com/luqmaansu/django-metachoices#readme
Project-URL: Repository, https://github.com/luqmaansu/django-metachoices
Project-URL: Bug Tracker, https://github.com/luqmaansu/django-metachoices/issues
Keywords: django,choices,metadata,fields
Classifier: Development Status :: 4 - Beta
Classifier: Framework :: Django
Classifier: Framework :: Django :: 5.2
Classifier: Intended Audience :: Developers
Classifier: Operating System :: OS Independent
Classifier: Programming Language :: Python
Classifier: Programming Language :: Python :: 3
Classifier: Programming Language :: Python :: 3.13
Classifier: Topic :: Software Development :: Libraries :: Python Modules
Classifier: Topic :: Database
Classifier: Topic :: Internet :: WWW/HTTP :: Dynamic Content
Requires-Python: >=3.10
License-File: LICENSE
Requires-Dist: Django>=4.2
Provides-Extra: dev
Requires-Dist: pytest>=7.0; extra == "dev"
Requires-Dist: pytest-django>=4.5.0; extra == "dev"
Requires-Dist: pytest-cov>=4.0; extra == "dev"
Requires-Dist: ruff>=0.1.0; extra == "dev"
Requires-Dist: mypy>=1.0.0; extra == "dev"
Requires-Dist: tox>=4.0.0; extra == "dev"
Provides-Extra: test
Requires-Dist: pytest>=7.0; extra == "test"
Requires-Dist: pytest-django>=4.5.0; extra == "test"
Requires-Dist: pytest-cov>=4.0; extra == "test"
Dynamic: license-file
